{
  "resourceType": "CarePlan",
  "id": "careplan-regimen-1",
  "meta": {
    "profile": [
      "http://canshare.co.nz/fhir/StructureDefinition/an-careplan-regimen"
    ]
  },
  "intent": "plan",
  "category": [
    {
      "coding": [
        {
          "code": "regimenCP",
          "system": "http://unknown.org"
        }
      ]
    }
  ],
  "identifier": [
    {
      "system": "http://canshare.co.nz/fhir/NamingSystem/1",
      "value": "abc"
    }
  ],
  "subject": {
    "reference": "Patient/exPatient"
  },
  "status": "completed",
  "extension": [
    {
      "url": "http://canshare.co.nz/fhir/StructureDefinition/an-iot",
      "valueCodeableConcept": {
        "coding": [
          {
            "code": "palliative",
            "system": "http://canshare.co.nz/fhir/CodeSystem/an-regimen-iot-cs"
          }
        ]
      }
    },
    {
      "url": "http://canshare.co.nz/fhir/StructureDefinition/an-clinical-trial",
      "valueBoolean": true
    },
    {
      "url": "http://hl7.org.nz/fhir/StructureDefinition/sact-regimen-type",
      "valueCodeableConcept": {
        "text": "FOLFOX"
      }
    }
  ],
  "period": {
    "start": "2012-01-01",
    "end": "2012-01-01"
  }
}
