{
  "resourceType": "Observation",
  "id": "excN1",
  "meta": {
    "profile": [
      "http://canshare.co.nz/fhir/StructureDefinition/an-cN"
    ]
  },
  "code": {
    "coding": [
      {
        "code": "399534004",
        "system": "http://snomed.info/sct"
      }
    ]
  },
  "subject": {
    "reference": "Patient/exPatient"
  },
  "status": "final",
  "valueCodeableConcept": {
    "coding": [
      {
        "code": "1229967007",
        "system": "http://snomed.info/sct",
        "display": "American Joint Committee on Cancer cN0 (qualifier value)"
      }
    ]
  }
}
